week_by_week/__init__.py
week_by_week/main.py
week_by_week-3.14.0.dist-info/WHEEL
week_by_week-3.14.0.dist-info/METADATA
week_by_week-3.14.0.dist-info/RECORD
