Metadata-Version: 2.1
Name: week-by-week
Version: 3.14.0
Summary: This Library accept pandas dataframe, date_column and optional end date If end date is not provide, current today will be use internally by the library
Home-page: https://github.com/blueband/week_by_week
License: MIT
Keywords: Pandas,Week by Week,Dataframe
Author: Qamarudeen Muhammad
Author-email: qamarudeen.m@gmail.com
Requires-Python: >=2.7,<3.0
Classifier: License :: OSI Approved :: MIT License
Classifier: Operating System :: OS Independent
Classifier: Programming Language :: Python :: 2
Classifier: Programming Language :: Python :: 2.7
Classifier: Topic :: Software Development :: Documentation
Classifier: Topic :: Software Development :: Libraries :: Python Modules
Classifier: Topic :: Software Development :: Quality Assurance
Requires-Dist: pandas (>=1.4.2,<2.0.0)
Project-URL: Repository, https://github.com/blueband/week_by_week
